pgextrascli-0.1.1.data/scripts/pgextrascli
pgextrascli-0.1.1.dist-info/WHEEL
pgextrascli-0.1.1.dist-info/top_level.txt
pgextrascli-0.1.1.dist-info/RECORD
pgextrascli-0.1.1.dist-info/DESCRIPTION.rst
pgextrascli-0.1.1.dist-info/pydist.json
pgextrascli-0.1.1.dist-info/METADATA
pgextrascli/__init__.py
pgextrascli/pgextrascli
