Metadata-Version: 2.0
Name: pgextrascli
Version: 0.1.1
Summary: Command line for pgextras
Home-page: https://github.com/onjin/pgextrascli
Author: Marek Wywiał
Author-email: onjinx@gmail.com
License: BSD
Keywords: pgextrascli
Platform: UNKNOWN
Classifier: Development Status :: 2 - Pre-Alpha
Classifier: Intended Audience :: Developers
Classifier: License :: OSI Approved :: BSD License
Classifier: Natural Language :: English
Classifier: Programming Language :: Python :: 2
Classifier: Programming Language :: Python :: 2.6
Classifier: Programming Language :: Python :: 2.7
Classifier: Programming Language :: Python :: 3
Classifier: Programming Language :: Python :: 3.3
Requires-Dist: click
Requires-Dist: pgextras
Requires-Dist: psycopg2
